bedway/__init__.py
bedway/app.py
bedway/auth.py
bedway/cli.py
bedway/log.py
bedway/schema.py
bedway/setting.py
bedway/models/__init__.py
bedway/models/base.py
bedway/models/bedrock.py
bedway/routers/__init__.py
bedway/routers/chat.py
bedway/routers/embeddings.py
bedway/routers/model.py
bedway-0.2.2.dist-info/METADATA
bedway-0.2.2.dist-info/WHEEL
bedway-0.2.2.dist-info/entry_points.txt
bedway-0.2.2.dist-info/licenses/LICENSE
bedway-0.2.2.dist-info/RECORD
