Metadata-Version: 2.4
Name: bedway
Version: 0.2.2
Summary: bedway
Project-URL: Source, https://github.com/wh1isper/bedway
Author-email: wh1isper <jizhongsheng957@gmail.com>
License: MIT license
License-File: LICENSE
Keywords: bedway
Classifier: Programming Language :: Python :: 3
Classifier: Programming Language :: Python :: 3.10
Classifier: Programming Language :: Python :: 3.11
Classifier: Programming Language :: Python :: 3.12
Requires-Python: >=3.10
Requires-Dist: boto3
Requires-Dist: botocore
Requires-Dist: click
Requires-Dist: fastapi
Requires-Dist: loguru
Requires-Dist: numpy
Requires-Dist: pydantic
Requires-Dist: requests
Requires-Dist: tiktoken
Requires-Dist: uvicorn[standard]
Provides-Extra: docs
Requires-Dist: autodoc-pydantic; extra == 'docs'
Requires-Dist: pydata-sphinx-theme; extra == 'docs'
Requires-Dist: sphinx; extra == 'docs'
Requires-Dist: sphinx-click; extra == 'docs'
Provides-Extra: test
Requires-Dist: boto3-stubs[bedrock,bedrock-runtime]; extra == 'test'
Requires-Dist: dirty-equals; extra == 'test'
Requires-Dist: pytest; extra == 'test'
Requires-Dist: pytest-asyncio; extra == 'test'
Requires-Dist: pytest-cov; extra == 'test'
